{"success":true,"code":"SUCCESS","data":{"states":null,"districts":[{"name":"imphal west","registereduser":185769},{"name":"imphal east","registereduser":120912},{"name":"thoubal","registereduser":57078},{"name":"bishnupur","registereduser":54415},{"name":"churachandpur","registereduser":47436},{"name":"kangpokpi","registereduser":38209},{"name":"kakching","registereduser":25649},{"name":"ukhrul","registereduser":18768},{"name":"tamenglong","registereduser":16084},{"name":"chandel","registereduser":13030}],"pincodes":[{"name":"795004","registereduser":86604},{"name":"795001","registereduser":35667},{"name":"795138","registereduser":27910},{"name":"795133","registereduser":27452},{"name":"795103","registereduser":23909},{"name":"795002","registereduser":20741},{"name":"795008","registereduser":20612},{"name":"795148","registereduser":19835},{"name":"795149","registereduser":19481},{"name":"795010","registereduser":19409}]},"responseTimestamp":1722517777061}