{"success":true,"code":"SUCCESS","data":{"states":null,"districts":[{"name":"khordha","registereduser":406689},{"name":"cuttack","registereduser":187723},{"name":"ganjam","registereduser":169386},{"name":"baleshwar","registereduser":139968},{"name":"jajapur","registereduser":114580},{"name":"sundargarh","registereduser":102838},{"name":"puri","registereduser":97920},{"name":"kendujhar","registereduser":83050},{"name":"bhadrak","registereduser":81249},{"name":"anugul","registereduser":76885}],"pincodes":[{"name":"751024","registereduser":27037},{"name":"751002","registereduser":25379},{"name":"751012","registereduser":24805},{"name":"760001","registereduser":23382},{"name":"751006","registereduser":23371},{"name":"756001","registereduser":23237},{"name":"751003","registereduser":21019},{"name":"751019","registereduser":19055},{"name":"753001","registereduser":18920},{"name":"751007","registereduser":18456}]},"responseTimestamp":1630501495231}