{"success":true,"code":"SUCCESS","data":{"states":null,"districts":[{"name":"ludhiana","registereduser":1476288},{"name":"sas nagar","registereduser":817209},{"name":"amritsar","registereduser":593970},{"name":"jalandhar","registereduser":560393},{"name":"patiala","registereduser":550482},{"name":"bathinda","registereduser":378864},{"name":"fazilka","registereduser":327088},{"name":"sangrur","registereduser":321129},{"name":"hoshiarpur","registereduser":274004},{"name":"gurdaspur","registereduser":247179}],"pincodes":[{"name":"143001","registereduser":378399},{"name":"141008","registereduser":211333},{"name":"141001","registereduser":128376},{"name":"147001","registereduser":120433},{"name":"140603","registereduser":120123},{"name":"140301","registereduser":115842},{"name":"141003","registereduser":114354},{"name":"145001","registereduser":100381},{"name":"141007","registereduser":95916},{"name":"144001","registereduser":90415}]},"responseTimestamp":1651127659626}