{"success":true,"code":"SUCCESS","data":{"hoverData":{"rayagada district":{"registereduser":38980,"appOpens":0},"koraput district":{"registereduser":45191,"appOpens":0},"malkangiri district":{"registereduser":10882,"appOpens":0},"sambalpur district":{"registereduser":79932,"appOpens":0},"kalahandi district":{"registereduser":55262,"appOpens":0},"anugul district":{"registereduser":97856,"appOpens":0},"ganjam district":{"registereduser":217114,"appOpens":0},"jajapur district":{"registereduser":149049,"appOpens":0},"bargarh district":{"registereduser":60736,"appOpens":0},"dhenkanal district":{"registereduser":81576,"appOpens":0},"bhadrak district":{"registereduser":105030,"appOpens":0},"nuapada district":{"registereduser":15932,"appOpens":0},"kendujhar district":{"registereduser":108387,"appOpens":0},"mayurbhanj district":{"registereduser":92892,"appOpens":0},"jharsuguda district":{"registereduser":57490,"appOpens":0},"kandhamal district":{"registereduser":20022,"appOpens":0},"deogarh district":{"registereduser":9725,"appOpens":0},"sundargarh district":{"registereduser":130288,"appOpens":0},"jagatsinghapur district":{"registereduser":87768,"appOpens":0},"balangir district":{"registereduser":64699,"appOpens":0},"baleshwar district":{"registereduser":180370,"appOpens":0},"puri district":{"registereduser":124859,"appOpens":0},"sonepur district":{"registereduser":29402,"appOpens":0},"khordha district":{"registereduser":499472,"appOpens":0},"boudh district":{"registereduser":16146,"appOpens":0},"gajapati district":{"registereduser":17730,"appOpens":0},"nayagarh district":{"registereduser":61134,"appOpens":0},"nabarangpur district":{"registereduser":18387,"appOpens":0},"kendrapara district":{"registereduser":80340,"appOpens":0},"cuttack district":{"registereduser":239067,"appOpens":0}}},"responseTimestamp":1630502911612}