{"success":true,"code":"SUCCESS","data":{"hoverData":{"udham singh nagar district":{"registereduser":418390,"appOpens":6671041},"haridwar district":{"registereduser":491252,"appOpens":8936480},"almora district":{"registereduser":72829,"appOpens":1336245},"pithoragarh district":{"registereduser":60279,"appOpens":1010673},"rudraprayag district":{"registereduser":30389,"appOpens":547787},"pauri garhwal district":{"registereduser":112287,"appOpens":1825649},"bageshwar district":{"registereduser":28329,"appOpens":461430},"champawat district":{"registereduser":33279,"appOpens":555158},"nainital district":{"registereduser":227497,"appOpens":3413516},"dehradun district":{"registereduser":711303,"appOpens":12440947},"chamoli district":{"registereduser":52184,"appOpens":906265},"uttarkashi district":{"registereduser":42144,"appOpens":749397},"tehri garhwal district":{"registereduser":85276,"appOpens":1522760}}},"responseTimestamp":1630502911966}