{"success":true,"code":"SUCCESS","data":{"states":null,"districts":[{"name":"khordha","registereduser":1924289},{"name":"cuttack","registereduser":1077286},{"name":"ganjam","registereduser":999398},{"name":"baleshwar","registereduser":769737},{"name":"jajapur","registereduser":672209},{"name":"sundargarh","registereduser":625606},{"name":"puri","registereduser":595694},{"name":"bhadrak","registereduser":507695},{"name":"kendujhar","registereduser":496154},{"name":"mayurbhanj","registereduser":451049}],"pincodes":[{"name":"751002","registereduser":125902},{"name":"751024","registereduser":117692},{"name":"751006","registereduser":110806},{"name":"753001","registereduser":105041},{"name":"760001","registereduser":103200},{"name":"751012","registereduser":95281},{"name":"756001","registereduser":95184},{"name":"751003","registereduser":90465},{"name":"752001","registereduser":90234},{"name":"751019","registereduser":88799}]},"responseTimestamp":1669732295440}