{"success":true,"code":"SUCCESS","data":{"hoverData":{"serchhip district":{"registereduser":5551,"appOpens":119776},"aizawl district":{"registereduser":68925,"appOpens":1314560},"lunglei district":{"registereduser":16676,"appOpens":464686},"mamit district":{"registereduser":7086,"appOpens":285294},"lawngtlai district":{"registereduser":13303,"appOpens":425324},"kolasib district":{"registereduser":9602,"appOpens":271438},"champhai district":{"registereduser":7814,"appOpens":170238},"saiha district":{"registereduser":3913,"appOpens":93235}}},"responseTimestamp":1674558327595}