{"success":true,"code":"SUCCESS","data":{"hoverData":{"south twenty four parganas district":{"registereduser":1118649,"appOpens":20403177},"purba bardhaman district":{"registereduser":688167,"appOpens":11910511},"uttar dinajpur district":{"registereduser":336911,"appOpens":6111418},"kalimpong district":{"registereduser":32223,"appOpens":482220},"murshidabad district":{"registereduser":1085899,"appOpens":16409710},"paschim medinipur district":{"registereduser":747114,"appOpens":14811586},"dakshin dinajpur district":{"registereduser":244088,"appOpens":3027085},"jalpaiguri district":{"registereduser":223198,"appOpens":4091384},"purulia district":{"registereduser":379046,"appOpens":6293502},"north twenty four parganas district":{"registereduser":2321888,"appOpens":48635786},"bankura district":{"registereduser":567358,"appOpens":9280342},"jhargram district":{"registereduser":108168,"appOpens":1997333},"howrah district":{"registereduser":875172,"appOpens":16024388},"hooghly district":{"registereduser":977339,"appOpens":19163716},"kolkata district":{"registereduser":1700474,"appOpens":33693299},"koch bihar district":{"registereduser":319131,"appOpens":5381867},"alipurduar district":{"registereduser":155176,"appOpens":2820482},"paschim bardhaman district":{"registereduser":688685,"appOpens":13025454},"nadia district":{"registereduser":832891,"appOpens":15442853},"birbhum district":{"registereduser":522435,"appOpens":8227523},"purba medinipur district":{"registereduser":824961,"appOpens":17526163},"maldah district":{"registereduser":568934,"appOpens":11028591},"darjiling district":{"registereduser":344186,"appOpens":5933529}}},"responseTimestamp":1630502912039}