{"success":true,"code":"SUCCESS","data":{"states":null,"districts":[{"name":"ahmadabad","registereduser":3445024},{"name":"surat","registereduser":2830392},{"name":"vadodara","registereduser":1210266},{"name":"rajkot","registereduser":782611},{"name":"gandhinagar","registereduser":706654},{"name":"banas kantha","registereduser":698841},{"name":"bharuch","registereduser":634589},{"name":"kachchh","registereduser":587589},{"name":"mahesana","registereduser":578072},{"name":"valsad","registereduser":565423}],"pincodes":[{"name":"395006","registereduser":340436},{"name":"395010","registereduser":231725},{"name":"394210","registereduser":231353},{"name":"395004","registereduser":168968},{"name":"395003","registereduser":167307},{"name":"382350","registereduser":163762},{"name":"396191","registereduser":150868},{"name":"382415","registereduser":140098},{"name":"382345","registereduser":130967},{"name":"385535","registereduser":128886}]},"responseTimestamp":1634575161293}