{"success":true,"code":"SUCCESS","data":{"states":null,"districts":[{"name":"hyderabad","registereduser":4962214},{"name":"rangareddy","registereduser":4296707},{"name":"medchal malkajgiri","registereduser":3628619},{"name":"sangareddy","registereduser":1159594},{"name":"warangal urban","registereduser":923715},{"name":"nalgonda","registereduser":793688},{"name":"khammam","registereduser":755705},{"name":"nizamabad","registereduser":729287},{"name":"karimnagar","registereduser":687385},{"name":"bhadradri kothagudem","registereduser":542203}],"pincodes":[{"name":"500072","registereduser":547282},{"name":"505001","registereduser":355528},{"name":"500018","registereduser":354983},{"name":"500008","registereduser":311735},{"name":"500055","registereduser":299618},{"name":"500037","registereduser":277467},{"name":"500039","registereduser":270128},{"name":"502032","registereduser":254815},{"name":"506002","registereduser":251886},{"name":"500013","registereduser":249027}]},"responseTimestamp":1674558313939}